electionnight/__init__.py
electionnight/apps.py
electionnight/celery.py
electionnight/conf.py
electionnight/exceptions.py
electionnight/fields.py
electionnight/signals.py
electionnight/widgets.py
electionnight/admin/__init__.py
electionnight/admin/ap_election_meta.py
electionnight/admin/candidate_election.py
electionnight/admin/color_order.py
electionnight/admin/page_content.py
electionnight/admin/votes.py
electionnight/bin/results.sh
electionnight/management/__init__.py
electionnight/management/commands/__init__.py
electionnight/management/commands/bake_elections.py
electionnight/management/commands/bootstrap_content.py
electionnight/management/commands/bootstrap_electionnight.py
electionnight/management/commands/bootstrap_electionnight_content.py
electionnight/management/commands/bootstrap_elex.py
electionnight/management/commands/bootstrap_ratings_from_prod.py
electionnight/management/commands/bootstrap_results_config.py
electionnight/management/commands/bootstrap_results_db.py
electionnight/management/commands/get_all_winners.py
electionnight/management/commands/get_house_votes.py
electionnight/management/commands/get_results.py
electionnight/management/commands/initialize_election_date_wrapped.py
electionnight/management/commands/prepare_zeroes.py
electionnight/management/commands/publish_zeroes.py
electionnight/management/commands/reup_to_db_wrapped.py
electionnight/management/commands/test_call.py
electionnight/management/commands/methods/__init__.py
electionnight/management/commands/methods/bootstrap/__init__.py
electionnight/management/commands/methods/bootstrap/executive_office.py
electionnight/management/commands/methods/bootstrap/executive_office_states.py
electionnight/management/commands/methods/bootstrap/general_election.py
electionnight/management/commands/methods/bootstrap/legislative_office.py
electionnight/management/commands/methods/bootstrap/special_election.py
politico_civic_election_night-0.13.5.dist-info/METADATA
politico_civic_election_night-0.13.5.dist-info/RECORD
politico_civic_election_night-0.13.5.dist-info/WHEEL
politico_civic_election_night-0.13.5.dist-info/top_level.txt
