Metadata-Version: 2.1
Name: politico-civic-election-night
Version: 0.13.5
Summary: UNKNOWN
Home-page: https://github.com/The-Politico/politico-civic-election-night
Author: POLITICO interactive news
Author-email: interactives@politico.com
License: MIT
Platform: UNKNOWN
Classifier: Development Status :: 3 - Alpha
Classifier: Framework :: Django
Classifier: Framework :: Django :: 2.0
Classifier: Intended Audience :: Developers
Classifier: Intended Audience :: Information Technology
Classifier: License :: OSI Approved :: MIT License
Classifier: Operating System :: OS Independent
Classifier: Programming Language :: Python :: 3
Classifier: Programming Language :: Python :: 3.5
Classifier: Programming Language :: Python :: 3.6
Classifier: Topic :: Internet :: WWW/HTTP
Provides-Extra: test
Requires-Dist: celery
Requires-Dist: django-cors-headers
Requires-Dist: django
Requires-Dist: djangorestframework
Requires-Dist: dj-database-url
Requires-Dist: elex
Requires-Dist: politico-civic-entity
Requires-Dist: politico-civic-geography
Requires-Dist: politico-civic-government
Requires-Dist: politico-civic-election
Requires-Dist: politico-civic-demography
Requires-Dist: politico-civic-vote
Requires-Dist: politico-civic-almanac
Requires-Dist: psycopg2
Requires-Dist: requests
Requires-Dist: slacker
Requires-Dist: python-twitter
Provides-Extra: test
Requires-Dist: pytest; extra == 'test'
